Metadata-Version: 2.1
Name: harshanandancalculator
Version: 0.0.1
Summary: A very basic calculator
Home-page: 
Author: Harsha Nandan
Author-email: madirajuharsha235@gmail.com
License: MIT
Keywords: calculator
Classifier: Development Status :: 5 - Production/Stable
Classifier: Intended Audience :: Education
Classifier: Operating System :: Microsoft :: Windows :: Windows 10
Classifier: License :: OSI Approved :: MIT License
Classifier: Programming Language :: Python :: 3
License-File: LICENSE.txt
